tests/__init__.py
tests/test_photos_db.py
update_photo_bookmarks/__init__.py
update_photo_bookmarks/chatbot_b.py
update_photo_bookmarks/photos_db.py
update_photo_bookmarks/update_photo_bookmarks.py
update_photo_bookmarks-0.2.1.dist-info/licenses/LICENSE
update_photo_bookmarks-0.2.1.dist-info/METADATA
update_photo_bookmarks-0.2.1.dist-info/WHEEL
update_photo_bookmarks-0.2.1.dist-info/entry_points.txt
update_photo_bookmarks-0.2.1.dist-info/top_level.txt
update_photo_bookmarks-0.2.1.dist-info/RECORD
