Metadata-Version: 2.4
Name: update_photo_bookmarks
Version: 0.2.1
Summary: A module for managing photo bookmarks in a mac OS photo librarydatabase
Home-page: https://github.com/geeheim/photobookmarks
Author: Geert Heilmann
Author-email: geert.heilmann@googlemail.com
Classifier: Programming Language :: Python :: 3
Classifier: License :: OSI Approved :: MIT License
Classifier: Operating System :: OS Independent
Requires-Python: >=3.6
License-File: LICENSE
Dynamic: author
Dynamic: author-email
Dynamic: classifier
Dynamic: description
Dynamic: description-content-type
Dynamic: home-page
Dynamic: license-file
Dynamic: requires-python
Dynamic: summary
